whatsapp_msg_spammer/__init__.py
whatsapp_msg_spammer/__main__.py
whatsapp_msg_spammer-0.2.1.dist-info/METADATA
whatsapp_msg_spammer-0.2.1.dist-info/WHEEL
whatsapp_msg_spammer-0.2.1.dist-info/entry_points.txt
whatsapp_msg_spammer-0.2.1.dist-info/top_level.txt
whatsapp_msg_spammer-0.2.1.dist-info/RECORD
