Metadata-Version: 2.1
Name: whatsapp-msg-spammer
Version: 0.2.1
Requires-Python: >=3.10
Requires-Dist: pyautogui
